[
    {"word":"LEAPERS","valid":true}
    ,{"word":"RELAPSE","valid":true}
    ,{"word":"PLEASER","valid":true}
    ,{"word":"REPEALS","valid":true}
    ,{"word":"PRESALE","valid":true}
    ,{"word":"ELAPSER","valid":false}
    ,{"word":"ABRADANT","valid":true}
    ,{"word":"TARABAND","valid":false}
    ,{"word":"STOCKCAR","valid":true}
    ,{"word":"COTRACKS","valid":false}
    ,{"word":"TIMOLOLS","valid":true}
    ,{"word":"MOTILLOS","valid":false}
    ,{"word":"MORAINIC","valid":true}
    ,{"word":"AMORINIC","valid":false}
    ,{"word":"BOATBILL","valid":true}
    ,{"word":"BILLBOAT","valid":false}
    ,{"word":"UPHROES","valid":true}
    ,{"word":"EPHORUS","valid":false}
    ,{"word":"REPOWER","valid":true}
    ,{"word":"POWERER","valid":false}
    ,{"word":"POPPLIER","valid":true}
    ,{"word":"PLOPPIER","valid":false}
    ,{"word":"COIFS","valid":true}
    ,{"word":"FICOS","valid":false}
    ,{"word":"FISHKILL","valid":true}
    ,{"word":"KILLFISH","valid":false}
    ,{"word":"FISHHOOK","valid":true}
    ,{"word":"HOOKFISH","valid":false}
    ,{"word":"ASTOMOUS","valid":true}
    ,{"word":"OSTAMOUS","valid":false}
    ,{"word":"COMSYMPS","valid":true}
    ,{"word":"SYMCOMPS","valid":false}
    ,{"word":"DIOPTRIC","valid":true}
    ,{"word":"TRIPODIC","valid":true}
    ,{"word":"DIPROTIC","valid":true}
    ,{"word":"TORPIDIC","valid":false}
    ,{"word":"TROILUS","valid":true}
    ,{"word":"URTISOL","valid":false}
    ,{"word":"SHIGELLA","valid":true}
    ,{"word":"SHEGILLA","valid":false}
    ,{"word":"PLICAS","valid":true}
    ,{"word":"SPICAL","valid":false}
    ,{"word":"SUBDUALS","valid":true}
    ,{"word":"SUBSUDAL","valid":false}
    ,{"word":"MARRONS","valid":true}
    ,{"word":"MORRANS","valid":false}
    ,{"word":"SILESIAS","valid":true}
    ,{"word":"LIASISES","valid":false}
    ,{"word":"ATHANASY","valid":true}
    ,{"word":"ANATHASY","valid":false}
    ,{"word":"NUANCING","valid":true}
    ,{"word":"UNCANING","valid":false}
    ,{"word":"PUPATES","valid":true}
    ,{"word":"PASTEUP","valid":true}
    ,{"word":"UPPASTE","valid":false}
    ,{"word":"DOSSERET","valid":true}
    ,{"word":"OERSTEDS","valid":true}
    ,{"word":"RETOSSED","valid":false}

]